doc/README.md
doc/events.md
doc/http.md
doc/loop.md
doc/tcp.md
doc/tls.md
doc/udp.md
test/framework.py
test/test_dns.py
test/test_events.py
test/test_graceful.py
test/test_http_client.py
test/test_http_parser.py
test/test_http_server.py
test/test_http_utils.py
test/test_loop.py
test/test_tcp_client.py
test/test_tcp_server.py
test/test_tcp_server_options.py
test/test_tls_client.py
test/test_udp.py
thor/__init__.py
thor/events.py
thor/loop.py
thor/py.typed
thor/tcp.py
thor/tls.py
thor/udp.py
thor/dns/__init__.py
thor/http/__init__.py
thor/http/common.py
thor/http/error.py
thor/http/server.py
thor/http/uri.py
thor/http/client/__init__.py
thor/http/client/__main__.py
thor/http/client/client.py
thor/http/client/connection.py
thor/http/client/exchange.py
thor/http/client/initiate.py
thor-0.12.5.dist-info/licenses/LICENSE.md
thor-0.12.5.dist-info/METADATA
thor-0.12.5.dist-info/WHEEL
thor-0.12.5.dist-info/top_level.txt
thor-0.12.5.dist-info/RECORD
