Metadata-Version: 2.4
Name: thor
Version: 0.12.5
Summary: Simple Event-Driven IO for Python
Author-email: Mark Nottingham <mnot@mnot.net>
License: # License
Project-URL: homepage, https://github.com/mnot/thor/
Classifier: Intended Audience :: Developers
Classifier: License :: OSI Approved :: MIT License
Classifier: Programming Language :: Python
Classifier: Operating System :: POSIX
Classifier: Topic :: Internet :: WWW/HTTP
Classifier: Topic :: Internet :: Proxy Servers
Classifier: Topic :: Internet :: WWW/HTTP :: HTTP Servers
Classifier: Topic :: Software Development :: Libraries :: Python Modules
Requires-Python: >=3.10
License-File: LICENSE.md
Requires-Dist: certifi
Requires-Dist: dnspython
Provides-Extra: dev
Requires-Dist: mypy; extra == "dev"
Requires-Dist: black; extra == "dev"
Requires-Dist: pylint; extra == "dev"
Requires-Dist: pytest; extra == "dev"
Requires-Dist: pytest-xdist; extra == "dev"
Requires-Dist: py; extra == "dev"
Requires-Dist: pytest-md; extra == "dev"
Requires-Dist: validate-pyproject; extra == "dev"
Requires-Dist: build; extra == "dev"
Dynamic: license-file
